mkdocs_order_button/__init__.py
mkdocs_order_button/mkdocs_order_button.py
mkdocs_order_button-0.1.0.dist-info/LICENSE
mkdocs_order_button-0.1.0.dist-info/METADATA
mkdocs_order_button-0.1.0.dist-info/WHEEL
mkdocs_order_button-0.1.0.dist-info/entry_points.txt
mkdocs_order_button-0.1.0.dist-info/top_level.txt
mkdocs_order_button-0.1.0.dist-info/RECORD
