Metadata-Version: 2.1
Name: mkdocs-order-button
Version: 0.1.0
Summary: Add your description here
License: Apache License
Requires-Python: >=3.10
License-File: LICENSE
Requires-Dist: markdown==3.3.0
Requires-Dist: mkdocs>=1.5.3
Requires-Dist: mkdocs-material>=9.5.18
Requires-Dist: plantuml-markdown>=3.10.4
Requires-Dist: pymdown-extensions>=10.4
